MANIFEST.in
README.rst
setup.py
src/sentry_penelope/__init__.py
src/sentry_penelope/api.py
src/sentry_penelope/models.py
src/sentry_penelope/plugin.py
src/sentry_penelope.egg-info/PKG-INFO
src/sentry_penelope.egg-info/SOURCES.txt
src/sentry_penelope.egg-info/dependency_links.txt
src/sentry_penelope.egg-info/entry_points.txt
src/sentry_penelope.egg-info/not-zip-safe
src/sentry_penelope.egg-info/requires.txt
src/sentry_penelope.egg-info/top_level.txt