Metadata-Version: 1.1
Name: sentry-penelope
Version: 0.1.1
Summary: A Sentry extension which integrates with penelope.
Home-page: http://github.com/getpenelope/sentry-penelope
Author: Andrew Mleczko
Author-email: penelopedev@redturtle.it
License: BSD
Platform: UNKNOWN
Classifier: Framework :: Django
Classifier: Intended Audience :: Developers
Classifier: Intended Audience :: System Administrators
Classifier: Operating System :: OS Independent
Classifier: Topic :: Software Development
